wagtail_neuralyzer/__init__.py
wagtail_neuralyzer/action.py
wagtail_neuralyzer/apps.py
wagtail_neuralyzer/menu_item.py
wagtail_neuralyzer/views.py
wagtail_neuralyzer/wagtail_hooks.py
wagtail_neuralyzer/locale/fr/LC_MESSAGES/django.mo
wagtail_neuralyzer/locale/fr/LC_MESSAGES/django.po
wagtail_neuralyzer/templates/wagtailadmin/generic/confirm_neuralyze.html
wagtail_neuralyzer/templates/wagtailadmin/wagtail_neuralyzer/bulk_actions/confirm_bulk_neuralyze.html
wagtail_neuralyzer/templates/wagtailadmin/wagtail_neuralyzer/bulk_actions/list_items_with_no_access.html
wagtail_neuralyzer-0.2.4.dist-info/licenses/LICENCE
wagtail_neuralyzer-0.2.4.dist-info/METADATA
wagtail_neuralyzer-0.2.4.dist-info/WHEEL
wagtail_neuralyzer-0.2.4.dist-info/top_level.txt
wagtail_neuralyzer-0.2.4.dist-info/RECORD
