Metadata-Version: 2.4
Name: wagtail-neuralyzer
Version: 0.2.4
Summary: Anonymize specific django model for specific instance - support for wagtail
Author-email: WebU dev team <contact@webu.coop>
Project-URL: Homepage, https://github.com/webu/wagtail-neuralyzer
Project-URL: Issues, https://github.com/webu/wagtail-neuralyzer/issues
Keywords: django,wagtail,anonymize
Classifier: Programming Language :: Python :: 3
Classifier: Framework :: Django
Classifier: Operating System :: OS Independent
Classifier: License :: OSI Approved :: MIT License
Requires-Python: >=3.6
License-File: LICENCE
Requires-Dist: django>=2.2
Requires-Dist: wagtail
Requires-Dist: django-neuralyzer
Dynamic: license-file
